glow/__init__.py
glow/_array.py
glow/_async.py
glow/_async.pyi
glow/_cache.py
glow/_cache.pyi
glow/_concurrency.py
glow/_concurrency.pyi
glow/_coro.py
glow/_debug.py
glow/_dev.py
glow/_futures.py
glow/_ic.py
glow/_import_hook.py
glow/_imutil.py
glow/_keys.py
glow/_logging.py
glow/_more.py
glow/_parallel.py
glow/_parallel.pyi
glow/_patch_len.py
glow/_patch_print.py
glow/_patch_scipy.py
glow/_profile.py
glow/_profile.pyi
glow/_reduction.py
glow/_repr.py
glow/_reusable.py
glow/_sizeof.py
glow/_streams.py
glow/_thread_quota.py
glow/_types.py
glow/_uuid.py
glow/_wrap.py
glow/cli.py
glow/cli.pyi
glow/py.typed
glow/api/__init__.py
glow/api/config.py
glow/api/exporting.py
glow/io/__init__.py
glow/io/_sound.py
glow/io/_svg.py
glow-0.15.7.dist-info/METADATA
glow-0.15.7.dist-info/WHEEL
glow-0.15.7.dist-info/licenses/LICENSE
glow-0.15.7.dist-info/RECORD
