Metadata-Version: 2.4
Name: glow
Version: 0.15.7
Summary: Functional Python tools
Project-URL: homepage, https://github.com/arquolo/glow
Author-email: Paul Maevskikh <arquolo@gmail.com>
Maintainer-email: Paul Maevskikh <arquolo@gmail.com>
License: MIT License
License-File: LICENSE
Classifier: Development Status :: 3 - Alpha
Classifier: License :: OSI Approved :: MIT License
Classifier: Operating System :: OS Independent
Classifier: Programming Language :: Python :: 3
Classifier: Programming Language :: Python :: 3.12
Classifier: Programming Language :: Python :: 3.13
Requires-Python: >=3.12
Requires-Dist: loguru
Requires-Dist: loky~=3.1
Requires-Dist: lxml
Requires-Dist: numpy<3,>=1.21
Requires-Dist: tqdm
Requires-Dist: typing-extensions~=4.1; python_version < '3.11'
Requires-Dist: typing-inspection~=0.4.1
Requires-Dist: wrapt~=1.15
Provides-Extra: all
Requires-Dist: asttokens; extra == 'all'
Requires-Dist: colorama; (sys_platform == 'win32') and extra == 'all'
Requires-Dist: executing; extra == 'all'
Requires-Dist: matplotlib; extra == 'all'
Requires-Dist: opencv-python-headless~=4.0; extra == 'all'
Requires-Dist: pygments; extra == 'all'
Requires-Dist: sounddevice; extra == 'all'
Requires-Dist: soundfile; extra == 'all'
Provides-Extra: dev
Requires-Dist: black~=25.1; extra == 'dev'
Requires-Dist: flake8-alphabetize; extra == 'dev'
Requires-Dist: flake8-pie; extra == 'dev'
Requires-Dist: flake8-pyi; extra == 'dev'
Requires-Dist: flake8-pyproject; extra == 'dev'
Requires-Dist: flake8-simplify; extra == 'dev'
Requires-Dist: flake8~=7.0; extra == 'dev'
Requires-Dist: isort; extra == 'dev'
Requires-Dist: mypy~=1.16; extra == 'dev'
Requires-Dist: pytest-asyncio; extra == 'dev'
Requires-Dist: pytest~=8.0; extra == 'dev'
Requires-Dist: ruff~=0.12.2; extra == 'dev'
Provides-Extra: dev-core
Requires-Dist: black~=25.1; extra == 'dev-core'
Requires-Dist: flake8-pie; extra == 'dev-core'
Requires-Dist: flake8-pyi; extra == 'dev-core'
Requires-Dist: flake8-pyproject; extra == 'dev-core'
Requires-Dist: flake8-simplify; extra == 'dev-core'
Requires-Dist: flake8~=7.0; extra == 'dev-core'
Requires-Dist: isort; extra == 'dev-core'
Requires-Dist: mypy~=1.16; extra == 'dev-core'
Requires-Dist: pytest-asyncio; extra == 'dev-core'
Requires-Dist: pytest~=8.0; extra == 'dev-core'
Requires-Dist: ruff~=0.12.2; extra == 'dev-core'
Provides-Extra: dev-wemake
Requires-Dist: black~=25.1; extra == 'dev-wemake'
Requires-Dist: flake8-pie; extra == 'dev-wemake'
Requires-Dist: flake8-pyi; extra == 'dev-wemake'
Requires-Dist: flake8-pyproject; extra == 'dev-wemake'
Requires-Dist: flake8-simplify; extra == 'dev-wemake'
Requires-Dist: flake8~=7.0; extra == 'dev-wemake'
Requires-Dist: isort; extra == 'dev-wemake'
Requires-Dist: mypy~=1.16; extra == 'dev-wemake'
Requires-Dist: pytest-asyncio; extra == 'dev-wemake'
Requires-Dist: pytest~=8.0; extra == 'dev-wemake'
Requires-Dist: ruff~=0.12.2; extra == 'dev-wemake'
Requires-Dist: wemake-python-styleguide~=1.3.0; extra == 'dev-wemake'
Provides-Extra: ic
Requires-Dist: asttokens; extra == 'ic'
Requires-Dist: colorama; (sys_platform == 'win32') and extra == 'ic'
Requires-Dist: executing; extra == 'ic'
Requires-Dist: pygments; extra == 'ic'
Provides-Extra: io
Requires-Dist: opencv-python-headless~=4.0; extra == 'io'
Requires-Dist: sounddevice; extra == 'io'
Requires-Dist: soundfile; extra == 'io'
Provides-Extra: memprof
Requires-Dist: psutil; extra == 'memprof'
